setup.py
pyesql/__init__.py
pyesql/parser.py
pyesql/tests.py
pyesql.egg-info/PKG-INFO
pyesql.egg-info/SOURCES.txt
pyesql.egg-info/dependency_links.txt
pyesql.egg-info/top_level.txt