Metadata-Version: 1.1
Name: pyesql
Version: 0.0.1
Summary: Python yesql clone
Home-page: https://github.com/KMahoney/pyesql
Author: UNKNOWN
Author-email: UNKNOWN
License: UNKNOWN
Platform: UNKNOWN
Classifier: Intended Audience :: Developers
Classifier: Programming Language :: Python
Classifier: Operating System :: OS Independent
